fryui/__init__.py
fryui/button.fw
fryui/grid.fw
fryui/icon.fw
fryui/link.fw
fryui-0.1.21.dist-info/METADATA
fryui-0.1.21.dist-info/WHEEL
fryui-0.1.21.dist-info/licenses/LICENSE
fryui-0.1.21.dist-info/RECORD
