Metadata-Version: 2.4
Name: fryui
Version: 0.1.21
Summary: A python web UI framework based on fryweb
Project-URL: Homepage, https://github.com/frybox/fryui
Project-URL: Bug Tracker, https://github.com/frybox/fryui/issues
Project-URL: Source, https://github.com/frybox/fryui
Author-email: Zenk Ju <juzejian@gmail.com>
License: MIT License
License-File: LICENSE
Keywords: fryui,fryweb
Classifier: License :: OSI Approved :: MIT License
Classifier: Operating System :: OS Independent
Classifier: Programming Language :: Python :: 3
Requires-Python: >=3.8
Requires-Dist: fryweb
